django_eth_events/__init__.py
django_eth_events/admin.py
django_eth_events/apps.py
django_eth_events/chainevents.py
django_eth_events/decoder.py
django_eth_events/event_listener.py
django_eth_events/exceptions.py
django_eth_events/factories.py
django_eth_events/models.py
django_eth_events/reorgs.py
django_eth_events/singleton.py
django_eth_events/tasks.py
django_eth_events/utils.py
django_eth_events/version.py
django_eth_events/web3_service.py
django_eth_events/management/__init__.py
django_eth_events/management/commands/__init__.py
django_eth_events/management/commands/resync_daemon.py
django_eth_events/migrations/0001_initial.py
django_eth_events/migrations/0002_daemon_last_error_block_number.py
django_eth_events/migrations/0003_block.py
django_eth_events/migrations/0004_auto_20171127_0501.py
django_eth_events/migrations/0005_daemon_status.py
django_eth_events/migrations/0006_block_timestamp.py
django_eth_events/migrations/0007_auto_20171207_0759.py
django_eth_events/migrations/0008_daemon_listener_lock.py
django_eth_events/migrations/0009_daemon_last_error_date_time.py
django_eth_events/migrations/__init__.py
django_eth_events/tests/__init__.py
django_eth_events/tests/mocked_testrpc_reorg.py
django_eth_events/tests/test_celery.py
django_eth_events/tests/test_daemon_model.py
django_eth_events/tests/test_decoder.py
django_eth_events/tests/test_event_listener_exec.py
django_eth_events/tests/test_event_listener_functions.py
django_eth_events/tests/test_reorg_detector.py
django_eth_events/tests/test_singleton.py
django_eth_events/tests/test_utils.py
django_eth_events/tests/test_web3_service.py
django_eth_events/tests/utils.py
helena_eth_events-3.1.9.data/data/LICENSE
helena_eth_events-3.1.9.dist-info/LICENSE
helena_eth_events-3.1.9.dist-info/METADATA
helena_eth_events-3.1.9.dist-info/WHEEL
helena_eth_events-3.1.9.dist-info/top_level.txt
helena_eth_events-3.1.9.dist-info/RECORD
